zotapaysdk/__init__.py
zotapaysdk/client.py
zotapaysdk/config.py
zotapaysdk/constants.py
zotapaysdk/exceptions.py
zotapaysdk/helpers.py
zotapaysdk/mg_comms.py
zotapaysdk/testing_tools.py
zotapaysdk/urls.py
zotapaysdk/mg_requests/__init__.py
zotapaysdk/mg_requests/callback.py
zotapaysdk/mg_requests/card_deposit_request.py
zotapaysdk/mg_requests/card_deposit_response.py
zotapaysdk/mg_requests/deposit_request.py
zotapaysdk/mg_requests/deposit_response.py
zotapaysdk/mg_requests/mg_request.py
zotapaysdk/mg_requests/objects.py
zotapaysdk/mg_requests/order_status_request.py
zotapaysdk/mg_requests/order_status_response.py
zotapaysdk/mg_requests/payout_request.py
zotapaysdk/mg_requests/payout_response.py
zotapaysdk/mg_requests/response.py
zotapaysdk/mg_requests/validation.py
zotapaysdk/tests/__init__.py
zotapaysdk/tests/conftest.py
zotapaysdk/tests/mocks.py
zotapaysdk/tests/local/__init__.py
zotapaysdk/tests/local/test_client_configuration.py
zotapaysdk/tests/local/test_core.py
zotapaysdk/tests/local/test_deposit.py
zotapaysdk/tests/local/test_order_status.py
zotapaysdk/tests/local/test_payout.py
zotapaysdk/tests/local/test_signatures.py
zotapaysdk/tests/online/__init__.py
zotapaysdk/tests/online/test_sandbox_deposit.py
zotapaysdk-1.1.6.dist-info/LICENSE
zotapaysdk-1.1.6.dist-info/METADATA
zotapaysdk-1.1.6.dist-info/WHEEL
zotapaysdk-1.1.6.dist-info/top_level.txt
zotapaysdk-1.1.6.dist-info/RECORD
