Metadata-Version: 2.1
Name: zotapaysdk
Version: 1.1.6
Summary: SDK Implementation of Zota's REST API for merchants.
Home-page: https://www.zotapay.com
Author: Zotapay Technology Limited
Author-email: Zota Technology LTD <open-source@zotapay.com>
License: Copyright 2020-2022 Zota Technology LTD        
Project-URL: Homepage, https://github.com/zotapay/python-sdk
Project-URL: Bug Tracker, https://github.com/zotapay/python-sdk/issues
Classifier: Development Status :: 6 - Mature
Classifier: Intended Audience :: Information Technology
Classifier: License :: OSI Approved :: Apache Software License
Classifier: Operating System :: OS Independent
Classifier: Programming Language :: Python :: 3
Classifier: Topic :: Software Development :: Libraries :: Python Modules
Requires-Python: >=3.6
License-File: LICENSE
Requires-Dist: requests
